nemo_tts/__init__.py
nemo_tts/data_layers.py
nemo_tts/tacotron2_modules.py
nemo_tts/waveglow_modules.py
nemo_tts/parts/__init__.py
nemo_tts/parts/datasets.py
nemo_tts/parts/helpers.py
nemo_tts/parts/layers.py
nemo_tts/parts/manifest.py
nemo_tts/parts/tacotron2.py
nemo_tts/parts/waveglow.py
nemo_tts-0.9.0.dist-info/LICENSE
nemo_tts-0.9.0.dist-info/METADATA
nemo_tts-0.9.0.dist-info/WHEEL
nemo_tts-0.9.0.dist-info/top_level.txt
nemo_tts-0.9.0.dist-info/RECORD
