Metadata-Version: 2.1
Name: nemo-tts
Version: 0.9.0
Summary: Collection of Neural Modules for Speech Synthesis
Home-page: https://github.com/nvidia/nemo
Author: NVIDIA
Author-email: nemo-toolkit@nvidia.com
License: UNKNOWN
Platform: UNKNOWN
Classifier: Programming Language :: Python :: 3
Classifier: Operating System :: OS Independent
Classifier: License :: OSI Approved :: Apache Software License
Requires-Dist: nemo-toolkit
Requires-Dist: nemo-asr
Requires-Dist: librosa
Requires-Dist: matplotlib
Requires-Dist: scipy
Requires-Dist: ruamel.yaml
Requires-Dist: pypinyin
